<?xml version="1.0" encoding="UTF-8" standalone="no"?><gameengine.controller.HighScoresKeeper>
  <changed>false</changed>
  <obs/>
  <myScores>
    <entry>
      <string>FlappyWithGunSound.xml</string>
      <tree-map>
        <entry>
          <string>Mateo</string>
          <int>30</int>
        </entry>
      </tree-map>
    </entry>
    <entry>
      <string>newFlappy.xml</string>
      <tree-map>
        <entry>
          <string>Blythe</string>
          <int>20</int>
        </entry>
      </tree-map>
    </entry>
    <entry>
      <string>michaelMario</string>
      <tree-map>
        <entry>
          <string>michael</string>
          <int>193</int>
        </entry>
      </tree-map>
    </entry>
  </myScores>
</gameengine.controller.HighScoresKeeper>